{
  "feature_id": "CC-0046",
  "title": "L001: Chaos Mesh FluxCD deployment infrastructure",
  "slug": "l001-chaos-mesh-fluxcd-deployment-infrastructure",
  "status": "proposed",
  "phase": null,
  "summary": "",
  "description": "**Size:** 📦 medium\n**Category:** infrastructure\n**Priority:** high\n**Source:** Proposed for '# GitHub Issue #132: Add negative and chaos E2E te'\n\nInstall Chaos Mesh into the kind cluster via FluxCD, following existing HelmRepository/HelmRelease conventions.\n\n1. **`deploy/flux-system/sources/chaos-mesh.yaml`** — HelmRepository CR pointing to Chaos Mesh chart registry (`interval: 1h`, matching `openbao.yaml`/`cert-manager.yaml` pattern)\n2. **`deploy/flux-system/releases/chaos-mesh.yaml`** — HelmRelease CR with `interval: 30m`, `dependsOn: [cert-manager]`, `install.crds: CreateReplace`, `upgrade.crds: CreateReplace`, `upgrade.remediation.retries: 3`, targeting `chaos-mesh` namespace (following `fluxcd-helmrelease-common-installupgrade-settings` pattern)\n3. **`deploy/flux-system/namespaces.yaml`** — Add `chaos-mesh` namespace declaration (following `two-phase-kustomization-for-crd-dependent-resources` pattern)\n4. **`deploy/flux-system/kustomization.yaml`** — Add chaos-mesh source and release to resource list\n5. **`deploy/kind/base/kustomization.yaml`** — Kind-specific overlay patch for Chaos Mesh (minimal resource limits, DNS config for kind networking)\n6. **`hack/deploy-infra.sh`** — Add `chaos-mesh` to Phase 2 `wait_for_helmreleases` list alongside existing operators (using existing `wait_for_helmreleases` helper, matching `infrastructure-deployment-script-with-8-step-orchestration` pattern)\n\nAll files use SPDX Apache-2.0 headers per `spdx-apache-20-header-on-infrastructure-files` pattern.\n\n**Rationale:** Chaos Mesh is the prerequisite for all chaos test scenarios. Without it installed and healthy in the kind cluster, no PodChaos or NetworkChaos CRs can be applied. This must land first so subsequent features can reference Chaos Mesh CRDs.\n\n**Affected Areas:**\n- deploy/flux-system/sources/chaos-mesh.yaml\n- deploy/flux-system/releases/chaos-mesh.yaml\n- deploy/flux-system/namespaces.yaml\n- deploy/flux-system/kustomization.yaml\n- deploy/kind/base/kustomization.yaml\n- hack/deploy-infra.sh",
  "stories": [],
  "requirements": [],
  "tasks": [],
  "test_specifications": [],
  "affected_files": [],
  "similar_patterns": [],
  "review_criteria": [],
  "implementation_notes": "",
  "status_history": {
    "proposed": {
      "github_account": "berendt",
      "timestamp": "2026-04-07T21:06:32.367588"
    }
  },
  "elaboration": "**Size:** 🏗️ large\n**Category:** infrastructure\n**Priority:** high\n\n---\n\n## Open Questions\n\nNo remaining open questions — all design decisions resolved.\n\n---\n\n## Summary\n\nAdd negative and chaos E2E test scenarios using Chaos Mesh to verify the Keystone operator recovers gracefully from infrastructure failures. This introduces a new `tests/e2e-chaos/` test suite with its own Chainsaw configuration (5m assert, 2m cleanup timeouts), Chaos Mesh CRD-based fault injection via a FluxCD HelmRelease, and a separate `e2e-chaos` CI job. The 8 scenarios cover pod kills (MariaDB, Memcached, OpenBao, operator, API pods with PDB), network faults (partition, latency), and CronJob failure detection — validating that status conditions degrade and recover correctly without the operator entering an unrecoverable state.\n\n## Scope\n\n**Included:**\n- Chaos Mesh installation as FluxCD HelmRelease + HelmRepository (following existing pattern in `deploy/flux-system/releases/` and `deploy/flux-system/sources/`)\n- Kind overlay patch for Chaos Mesh (minimal resource config, matching `deploy/kind/base/kustomization.yaml` pattern)\n- Extension of `hack/deploy-infra.sh` to wait for Chaos Mesh HelmRelease readiness (using existing `wait_for_helmreleases` helper)\n- New `tests/e2e-chaos/` directory with dedicated `chainsaw-config.yaml` (5m assert, 2m cleanup, parallel 2, JUnit XML to `_output/reports`)\n- SC-CHAOS-001: MariaDB pod kill → `DatabaseReady=False` → recovery to `Ready=True`\n- SC-CHAOS-002: Memcached pod kill → degraded performance, no condition regression\n- SC-CHAOS-003: OpenBao pod kill → `SecretsReady=False` on next secret sync → recovery\n- SC-CHAOS-004: Operator pod kill mid-reconcile → controller-runtime restart → re-reconcile to `Ready=True`\n- SC-CHAOS-005: CronJob rotation failure via PodChaos on CronJob-spawned pods → failed Job detection → operator status reflects failure\n- SC-CHAOS-006: Network partition between operator and MariaDB → `DatabaseReady=False` → recovery after heal\n- SC-CHAOS-007: Network latency injection → operator tolerates slow responses without crash-looping\n- SC-CHAOS-008: API pod kill with PDB respected → PDB prevents all-at-once termination\n- Each test directory follows existing naming convention: kebab-case directory, `chainsaw-test.yaml`, numbered resource files (`00-keystone-cr.yaml`, `01-podchaos.yaml`, etc.)\n- Diagnostic `catch` blocks in all tests (pod logs with `--previous`, events, describe — matching existing E2E pattern in `tests/e2e/keystone/`)\n- Makefile target `e2e-chaos`: `chainsaw test --config tests/e2e-chaos/chainsaw-config.yaml tests/e2e-chaos/`\n- GitHub Actions job `e2e-chaos` in `.github/workflows/ci.yaml` (triggered on `main` push or `run-chaos` PR label, separate from existing `e2e-operator` job)\n- Shared Keystone CR fixture reused from `tests/e2e/keystone/basic-deployment/00-keystone-cr.yaml` pattern\n\n**Excluded:**\n- SC-CHAOS-009 through SC-CHAOS-013 (multi-dependency failures, FluxCD restart, ESO controller restart) — YAGNI: not requested, can be added incrementally\n- Chaos testing for the c5c3 operator — no happy-path E2E tests exist for it yet; chaos tests should follow happy-path\n- Continuous chaos / steady-state chaos in staging — out of scope, this is CI-triggered testing only\n- Custom Chaos Mesh dashboards or monitoring — not needed for CI execution\n- Modifications to the operator's reconciliation logic — tests validate existing behavior, not new features\n- Changes to existing happy-path E2E tests or their Chainsaw config\n\n## Visualization\n\n```mermaid\nflowchart TD\n    subgraph CI[\"GitHub Actions: e2e-chaos job\"]\n        trigger[\"Push to main / run-chaos label\"]\n        trigger --> deploy[\"hack/deploy-infra.sh\"]\n        deploy --> chaos_hr[\"FluxCD reconciles Chaos Mesh HelmRelease\"]\n        chaos_hr --> build[\"Build + Load Operator Image\"]\n        build --> helm[\"Helm install keystone-operator\"]\n        helm --> run[\"chainsaw test tests/e2e-chaos/\"]\n        run --> report[\"JUnit XML to _output/reports\"]\n    end\n\n    subgraph Infra[\"deploy/flux-system/ additions\"]\n        src[\"sources/chaos-mesh.yaml HelmRepository\"]\n        rel[\"releases/chaos-mesh.yaml HelmRelease\"]\n        patch[\"deploy/kind/base/ kustomization patch\"]\n    end\n\n    subgraph Tests[\"tests/e2e-chaos/\"]\n        cfg[\"chainsaw-config.yaml\"]\n        pod_faults[\"Pod Faults\"]\n        net_faults[\"Network Faults\"]\n        cron_fail[\"CronJob Failure\"]\n        pod_faults --> SC001[\"mariadb-pod-kill/\"]\n        pod_faults --> SC002[\"memcached-pod-kill/\"]\n        pod_faults --> SC003[\"openbao-pod-kill/\"]\n        pod_faults --> SC004[\"operator-pod-crash/\"]\n        pod_faults --> SC008[\"api-pod-kill-pdb/\"]\n        net_faults --> SC006[\"network-partition/\"]\n        net_faults --> SC007[\"network-latency/\"]\n        cron_fail --> SC005[\"cronjob-rotation-failure/\"]\n    end\n```\n\n```mermaid\nsequenceDiagram\n    participant CH as Chainsaw Test\n    participant CM as Chaos Mesh\n    participant OP as Keystone Operator\n    participant DB as MariaDB Pod\n    participant KA as Kubernetes API\n\n    CH->>KA: Apply 00-keystone-cr.yaml\n    CH->>KA: Assert Ready=True, reason=AllReady\n    CH->>KA: Apply 01-podchaos.yaml targeting MariaDB\n    CM->>DB: Kill pod\n    CH->>KA: Assert DatabaseReady=False\n    Note over DB: StatefulSet restarts pod\n    CH->>KA: Assert DatabaseReady=True\n    CH->>KA: Assert Ready=True, reason=AllReady\n    CH->>KA: Delete PodChaos CR\n```\n\n```mermaid\nstateDiagram-v2\n    [*] --> Ready: Initial reconciliation complete\n    Ready --> Degraded: Chaos fault injected\n    Degraded --> Recovering: Fault healed / pod restarted\n    Recovering --> Ready: Operator re-reconciles successfully\n    Ready --> [*]: Test passes\n\n    state Degraded {\n        [*] --> DatabaseReadyFalse: MariaDB kill / network partition\n        [*] --> SecretsReadyFalse: OpenBao kill\n        [*] --> OperatorRestart: Operator kill\n        [*] --> CronJobFailed: Rotation failure\n        [*] --> PDBEnforced: API pod kill with PDB\n    }\n```\n\n## Key Components\n\n- **`deploy/flux-system/sources/chaos-mesh.yaml`**: HelmRepository CR pointing to Chaos Mesh chart registry (following `openbao.yaml`, `cert-manager.yaml` pattern: `interval: 1h`)\n- **`deploy/flux-system/releases/chaos-mesh.yaml`**: HelmRelease CR with `interval: 30m`, `dependsOn: [cert-manager]`, `install.crds: CreateReplace`, `upgrade.remediation.retries: 3` — matching existing HelmRelease conventions; targets `chaos-mesh` namespace\n- **`deploy/kind/base/kustomization.yaml` patch**: Kind-specific Chaos Mesh values (reduced resources, DNS config for kind networking) — added to existing kustomization resources list\n- **`hack/deploy-infra.sh` extension**: Add `chaos-mesh` to the Phase 2 `wait_for_helmreleases` list (alongside `openbao`, `mariadb-operator`, `external-secrets`, `memcached-operator`)\n- **`tests/e2e-chaos/chainsaw-config.yaml`**: Dedicated Chainsaw v0.2.14 config — `assert: 5m`, `cleanup: 2m`, `parallel: 2` (lower than happy-path's 4 due to resource contention), `failFast: true`, JUnit XML to `_output/reports`\n- **`tests/e2e-chaos/<scenario>/chainsaw-test.yaml`**: 8 test directories (kebab-case), each containing `chainsaw-test.yaml` + numbered resource files (`00-keystone-cr.yaml`, `01-podchaos.yaml` or `01-networkchaos.yaml`), with SPDX headers and CC-0046 feature ID references\n- **Chaos Mesh CRDs**: `PodChaos` resources for SC-001–005, SC-008 (pod-kill/pod-failure actions with label selectors); `NetworkChaos` resources for SC-006 (partition action) and SC-007 (delay action with latency/jitter)\n- **`Makefile` target `e2e-chaos`**: `chainsaw test --config tests/e2e-chaos/chainsaw-config.yaml tests/e2e-chaos/` — parallel to existing `e2e` target\n- **`.github/workflows/ci.yaml` job `e2e-chaos`**: Separate job with 45m timeout (matching `e2e-operator`), triggered by `main` push or `run-chaos` label filter, depends on `lint + shellcheck + test + test-integration + verify-codegen`, follows same kind cluster setup → deploy-infra → build → helm install → chainsaw test flow as `e2e-operator`, uploads JUnit artifact as `e2e-chaos-junit-report`"
}
